nixt/brokers.py
nixt/clients.py
nixt/command.py
nixt/configs.py
nixt/defines.py
nixt/handler.py
nixt/loggers.py
nixt/message.py
nixt/methods.py
nixt/objects.py
nixt/persist.py
nixt/repeats.py
nixt/serials.py
nixt/statics.py
nixt/threads.py
nixt/timings.py
nixt/utility.py
nixt/workdir.py
nixt/modules/__init__.py
nixt/network/__init__.py
nixt/nucleus/__init__.py
nixt-451.dist-info/METADATA
nixt-451.dist-info/WHEEL
nixt-451.dist-info/top_level.txt
nixt-451.dist-info/RECORD
