Metadata-Version: 2.4
Name: nixt
Version: 451
Summary: NIXT
Author-email: Nixt Niet <nixtniet@gmail.com>
License-Expression: Unlicense
Project-URL: home, https://pypi.org/project/nixt
Project-URL: bugs, https://github.com/nixtniet/nixt/issues
Project-URL: source, https://github.com/nixtniet/nixt
Classifier: Development Status :: 3 - Alpha
Classifier: Operating System :: Unix
Classifier: Programming Language :: Python :: 3
Classifier: Topic :: Utilities
